README.md
setup.py
bluesales_python_sdk.egg-info/PKG-INFO
bluesales_python_sdk.egg-info/SOURCES.txt
bluesales_python_sdk.egg-info/dependency_links.txt
bluesales_python_sdk.egg-info/top_level.txt
bluesalespy/__init__.py
bluesalespy/bluesales.py
bluesalespy/customersapi.py
bluesalespy/exceptions.py
bluesalespy/methods.py
bluesalespy/ordersapi.py
bluesalespy/request.py
bluesalespy/test_sample.py
bluesalespy/usersapi.py