Metadata-Version: 1.0
Name: bluesales-python-sdk
Version: 1.0.0
Summary: Simple way to call BlueSales API
Home-page: https://github.com/thehighestmath/bluesales-python-sdk
Author: therealyou
Author-email: kirill.lfybk.rh@gmail.com 
License: GPL-3.0 License
Platform: UNKNOWN
